{"name":"Guysafternoonin.github.io","tagline":"","body":"## Welcome to the GuysAfternoonIn Page.\r\nThis just being tested out at the moment as I try to bring in additional functionality for collaboration in the GuysAfternoonIn team.\r\n\r\n```\r\n$ cd your_repo_root/repo_name\r\n$ git fetch origin\r\n$ git checkout gh-pages\r\n```\r\n```\r\n> test command line\r\n```\r\n```\r\nvoid method()\r\n{\r\n    if (dogsCanLookUp)\r\n    {\r\n        mindBlow = true;\r\n    }\r\n    else\r\n    {\r\n        feelValidated = true;\r\n    }\r\n}\r\n```\r\n\r\n### Current Members\r\nJake Wondra (@jwondra)","google":"","note":"Don't delete this file! It's used internally to help with page regeneration."}